Metadata-Version: 1.1
Name: easy-cord-python
Version: 1.0.1
Summary: Łatwiejszy bot w pythonie
Home-page: UNKNOWN
Author: lisior
Author-email: kox123koz@gmail.com
License: MIT
Platform: UNKNOWN
Classifier: Development Status :: 5 - Production/Stable
Classifier: Intended Audience :: Education
Classifier: Operating System :: Microsoft :: Windows :: Windows 10
Classifier: License :: OSI Approved :: MIT License
Classifier: Programming Language :: Python :: 3
